{
  "project_info": {
    "project_number": "578010305596",
    "project_id": "neurotribo-1bd8e",
    "storage_bucket": "neurotribo-1bd8e.firebasestorage.app"
  },
  "client": [
    {
      "client_info": {
        "mobilesdk_app_id": "1:578010305596:android:6fb20c1cb0d0158dd25f39",
        "android_client_info": {
          "package_name": "com.example.neuro_tribo"
        }
      },
      "oauth_client": [
        {
          "client_id": "578010305596-ukc5lsgi0bta0dkgtd541jclvp00d9d0.apps.googleusercontent.com",
          "client_type": 1,
          "android_info": {
            "package_name": "com.example.neuro_tribo",
            "certificate_hash": "d2f2ab2aa65979812eb76e0e8f0abb278a72e0d0"
          }
        },
        {
          "client_id": "578010305596-eua4588c489mqoc91jrh6202mg4mu1p6.apps.googleusercontent.com",
          "client_type": 3
        }
      ],
      "api_key": [
        {
          "current_key": "AIzaSyCdW67tVz7l9lcx3VzVDdRSVB76iYNyjv0"
        }
      ],
      "services": {
        "appinvite_service": {
          "other_platform_oauth_client": [
            {
              "client_id": "578010305596-eua4588c489mqoc91jrh6202mg4mu1p6.apps.googleusercontent.com",
              "client_type": 3
            },
            {
              "client_id": "578010305596-l00j8msac1knhh6e00n2678rnhnhl2pr.apps.googleusercontent.com",
              "client_type": 2,
              "ios_info": {
                "bundle_id": "com.example.neuroTribo"
              }
            }
          ]
        }
      }
    }
  ],
  "configuration_version": "1"
}